daletou/__init__.py
daletou/dlt.py
daletou_OceanWang-0.0.1.dist-info/LICENSE
daletou_OceanWang-0.0.1.dist-info/METADATA
daletou_OceanWang-0.0.1.dist-info/WHEEL
daletou_OceanWang-0.0.1.dist-info/top_level.txt
daletou_OceanWang-0.0.1.dist-info/RECORD
