Metadata-Version: 2.1
Name: daletou-OceanWang
Version: 0.0.1
Summary: dlt example package
Author: Author
Author-email: 37537529@qq.com
Requires-Python: >=3.6
License-File: LICENSE
